jujuna/__init__.py
jujuna/__main__.py
jujuna/clean.py
jujuna/deploy.py
jujuna/helper.py
jujuna/settings.py
jujuna/tests.py
jujuna/upgrade.py
jujuna/brokers/__init__.py
jujuna/brokers/api.py
jujuna/brokers/file.py
jujuna/brokers/mount.py
jujuna/brokers/network.py
jujuna/brokers/package.py
jujuna/brokers/process.py
jujuna/brokers/service.py
jujuna/brokers/user.py
jujuna/exporters/__init__.py
jujuna/exporters/file.py
jujuna/exporters/mount.py
jujuna/exporters/network.py
jujuna/exporters/package.py
jujuna/exporters/process.py
jujuna/exporters/service.py
jujuna/exporters/user.py
jujuna-2.8.0.dist-info/LICENSE
jujuna-2.8.0.dist-info/METADATA
jujuna-2.8.0.dist-info/WHEEL
jujuna-2.8.0.dist-info/entry_points.txt
jujuna-2.8.0.dist-info/top_level.txt
jujuna-2.8.0.dist-info/RECORD
