Metadata-Version: 2.1
Name: jujuna
Version: 2.8.0
Summary: Continuous deployment, upgrade and testing for Juju.
Home-page: https://github.com/huntdatacenter/jujuna
Author: Matus Kosut
Author-email: matuskosut@gmail.com
Maintainer: HUNT Data Center
Maintainer-email: cloud@hunt.ntnu.no
License: Apache 2
Platform: UNKNOWN
Classifier: Development Status :: 4 - Beta
Classifier: Programming Language :: Python :: 3.5
Classifier: Programming Language :: Python :: 3.6
Classifier: Programming Language :: Python :: 3.7
Classifier: Programming Language :: Python :: 3.8
Classifier: Programming Language :: Python :: 3.9
Classifier: License :: OSI Approved :: Apache Software License
Classifier: Operating System :: POSIX :: Linux
Classifier: Environment :: Console
Requires-Dist: async-timeout (<4.0.0,>=2.0.1)
Requires-Dist: argcomplete (==1.10.0)
Requires-Dist: theblues (<1.0.0,>=0.5.2)
Requires-Dist: juju (<1.0.0,>=0.11.7) ; python_version<='3.5.2'
Requires-Dist: pyyaml (<=4.2,>=3.0) ; python_version<='3.5.2'
Requires-Dist: juju (<2.9.0,>=2.8.0) ; python_version>'3.5.2'
Requires-Dist: pyyaml (<6.0,>=3.0) ; python_version>'3.5.2'
